ai_summarizer/__init__.py
ai_summarizer/init.py
ai_summarizer/main.py
AI_Summarizer-1.0.4.dist-info/METADATA
AI_Summarizer-1.0.4.dist-info/WHEEL
AI_Summarizer-1.0.4.dist-info/top_level.txt
AI_Summarizer-1.0.4.dist-info/RECORD
